mule_validator/__init__.py
mule_validator/api_validator.py
mule_validator/code_reviewer.py
mule_validator/configfile_validator.py
mule_validator/dependency_validator.py
mule_validator/flow_validator.py
mule_validator/html_reporter.py
mule_validator/logs_reviewer.py
mule_validator/main.py
mule_validator/mule_orphan_checker.py
mule_validator/report_template.html
mule_validator/reporter.py
mule_validator/security_patterns.py
mulesoft_package_validator-1.0.0.dist-info/licenses/LICENSE
mulesoft_package_validator-1.0.0.dist-info/METADATA
mulesoft_package_validator-1.0.0.dist-info/WHEEL
mulesoft_package_validator-1.0.0.dist-info/entry_points.txt
mulesoft_package_validator-1.0.0.dist-info/top_level.txt
mulesoft_package_validator-1.0.0.dist-info/RECORD
