Metadata-Version: 2.4
Name: mulesoft-package-validator
Version: 1.0.0
Summary: Comprehensive validation tool for MuleSoft projects
Home-page: https://github.com/venkat-training/mulesoft_package_validator
Author: Venkat
Author-email: venkiwm@gmail.com
Project-URL: Bug Reports, https://github.com/venkat-training/mulesoft_package_validator/issues
Project-URL: Source, https://github.com/venkat-training/mulesoft_package_validator
Keywords: mulesoft validation testing quality-assurance security
Classifier: Development Status :: 4 - Beta
Classifier: Intended Audience :: Developers
Classifier: Topic :: Software Development :: Quality Assurance
Classifier: License :: OSI Approved :: MIT License
Classifier: Programming Language :: Python :: 3
Classifier: Programming Language :: Python :: 3.8
Classifier: Programming Language :: Python :: 3.9
Classifier: Programming Language :: Python :: 3.10
Classifier: Programming Language :: Python :: 3.11
Classifier: Programming Language :: Python :: 3.12
Requires-Python: >=3.8
License-File: LICENSE
Requires-Dist: lxml>=4.9.0
Requires-Dist: tabulate>=0.9.0
Requires-Dist: PyYAML>=6.0
Provides-Extra: dev
Requires-Dist: pytest>=7.0.0; extra == "dev"
Requires-Dist: pytest-cov>=3.0.0; extra == "dev"
Requires-Dist: black>=22.0.0; extra == "dev"
Requires-Dist: flake8>=4.0.0; extra == "dev"
Requires-Dist: mypy>=0.950; extra == "dev"
Dynamic: author
Dynamic: author-email
Dynamic: classifier
Dynamic: description
Dynamic: description-content-type
Dynamic: home-page
Dynamic: keywords
Dynamic: license-file
Dynamic: project-url
Dynamic: provides-extra
Dynamic: requires-dist
Dynamic: requires-python
Dynamic: summary
